{
    "Scope":  {
                  "IsConnected":  true,
                  "Options":  "System.Management.ConnectionOptions",
                  "Path":  "\\\\localhost\\root\\cimv2"
              },
    "Path":  {
                 "Path":  "\\\\DESKTOP-NE4F0PQ\\root\\cimv2:Win32_OperatingSystem=@",
                 "RelativePath":  "Win32_OperatingSystem=@",
                 "Server":  "DESKTOP-NE4F0PQ",
                 "NamespacePath":  "root\\cimv2",
                 "ClassName":  "Win32_OperatingSystem",
                 "IsClass":  false,
                 "IsInstance":  true,
                 "IsSingleton":  true
             },
    "Options":  {
                    "UseAmendedQualifiers":  false,
                    "Context":  "",
                    "Timeout":  "10675199.02:48:05.4775807"
                },
    "ClassPath":  {
                      "Path":  "\\\\DESKTOP-NE4F0PQ\\root\\cimv2:Win32_OperatingSystem",
                      "RelativePath":  "Win32_OperatingSystem",
                      "Server":  "DESKTOP-NE4F0PQ",
                      "NamespacePath":  "root\\cimv2",
                      "ClassName":  "Win32_OperatingSystem",
                      "IsClass":  true,
                      "IsInstance":  false,
                      "IsSingleton":  false
                  },
    "Properties":  [
                       "System.Management.PropertyData",
                       "System.Management.PropertyData",
                       "System.Management.PropertyData",
                       "System.Management.PropertyData",
                       "System.Management.PropertyData",
                       "System.Management.PropertyData",
                       "System.Management.PropertyData",
                       "System.Management.PropertyData",
                       "System.Management.PropertyData",
                       "System.Management.PropertyData",
                       "System.Management.PropertyData",
                       "System.Management.PropertyData",
                       "System.Management.PropertyData",
                       "System.Management.PropertyData",
                       "System.Management.PropertyData",
                       "System.Management.PropertyData",
                       "System.Management.PropertyData",
                       "System.Management.PropertyData",
                       "System.Management.PropertyData",
                       "System.Management.PropertyData",
                       "System.Management.PropertyData",
                       "System.Management.PropertyData",
                       "System.Management.PropertyData",
                       "System.Management.PropertyData",
                       "System.Management.PropertyData",
                       "System.Management.PropertyData",
                       "System.Management.PropertyData",
                       "System.Management.PropertyData",
                       "System.Management.PropertyData",
                       "System.Management.PropertyData",
                       "System.Management.PropertyData",
                       "System.Management.PropertyData",
                       "System.Management.PropertyData",
                       "System.Management.PropertyData",
                       "System.Management.PropertyData",
                       "System.Management.PropertyData",
                       "System.Management.PropertyData",
                       "System.Management.PropertyData",
                       "System.Management.PropertyData",
                       "System.Management.PropertyData",
                       "System.Management.PropertyData",
                       "System.Management.PropertyData",
                       "System.Management.PropertyData",
                       "System.Management.PropertyData",
                       "System.Management.PropertyData",
                       "System.Management.PropertyData",
                       "System.Management.PropertyData",
                       "System.Management.PropertyData",
                       "System.Management.PropertyData",
                       "System.Management.PropertyData",
                       "System.Management.PropertyData",
                       "System.Management.PropertyData",
                       "System.Management.PropertyData",
                       "System.Management.PropertyData",
                       "System.Management.PropertyData",
                       "System.Management.PropertyData",
                       "System.Management.PropertyData",
                       "System.Management.PropertyData",
                       "System.Management.PropertyData",
                       "System.Management.PropertyData",
                       "System.Management.PropertyData",
                       "System.Management.PropertyData",
                       "System.Management.PropertyData",
                       "System.Management.PropertyData"
                   ],
    "SystemProperties":  [
                             "System.Management.PropertyData",
                             "System.Management.PropertyData",
                             "System.Management.PropertyData",
                             "System.Management.PropertyData",
                             "System.Management.PropertyData",
                             "System.Management.PropertyData",
                             "System.Management.PropertyData",
                             "System.Management.PropertyData",
                             "System.Management.PropertyData",
                             "System.Management.PropertyData"
                         ],
    "Qualifiers":  [
                       "System.Management.QualifierData",
                       "System.Management.QualifierData",
                       "System.Management.QualifierData",
                       "System.Management.QualifierData",
                       "System.Management.QualifierData"
                   ],
    "Site":  null,
    "Container":  null,
    "PSComputerName":  "DESKTOP-NE4F0PQ",
    "__GENUS":  2,
    "__CLASS":  "Win32_OperatingSystem",
    "__SUPERCLASS":  "CIM_OperatingSystem",
    "__DYNASTY":  "CIM_ManagedSystemElement",
    "__RELPATH":  "Win32_OperatingSystem=@",
    "__PROPERTY_COUNT":  64,
    "__DERIVATION":  [
                         "CIM_OperatingSystem",
                         "CIM_LogicalElement",
                         "CIM_ManagedSystemElement"
                     ],
    "__SERVER":  "DESKTOP-NE4F0PQ",
    "__NAMESPACE":  "root\\cimv2",
    "__PATH":  "\\\\DESKTOP-NE4F0PQ\\root\\cimv2:Win32_OperatingSystem=@",
    "BootDevice":  "\\Device\\HarddiskVolume1",
    "BuildNumber":  "19042",
    "BuildType":  "Multiprocessor Free",
    "Caption":  "Microsoft Windows 10 Pro",
    "CodeSet":  "1250",
    "CountryCode":  "420",
    "CreationClassName":  "Win32_OperatingSystem",
    "CSCreationClassName":  "Win32_ComputerSystem",
    "CSDVersion":  null,
    "CSName":  "DESKTOP-NE4F0PQ",
    "CurrentTimeZone":  120,
    "DataExecutionPrevention_32BitApplications":  true,
    "DataExecutionPrevention_Available":  true,
    "DataExecutionPrevention_Drivers":  true,
    "DataExecutionPrevention_SupportPolicy":  2,
    "Debug":  false,
    "Description":  "",
    "Distributed":  false,
    "EncryptionLevel":  256,
    "ForegroundApplicationBoost":  2,
    "FreePhysicalMemory":  3984320,
    "FreeSpaceInPagingFiles":  6018508,
    "FreeVirtualMemory":  9795260,
    "InstallDate":  "20210419002027.000000+120",
    "LargeSystemCache":  null,
    "LastBootUpTime":  "20210427160433.500000+120",
    "LocalDateTime":  "20210427173752.752000+120",
    "Locale":  "0405",
    "Manufacturer":  "Microsoft Corporation",
    "MaxNumberOfProcesses":  4294967295,
    "MaxProcessMemorySize":  137438953344,
    "MUILanguages":  [
                         "cs-CZ"
                     ],
    "Name":  "Microsoft Windows 10 Pro|C:\\WINDOWS|\\Device\\Harddisk0\\Partition2",
    "NumberOfLicensedUsers":  null,
    "NumberOfProcesses":  191,
    "NumberOfUsers":  2,
    "OperatingSystemSKU":  48,
    "Organization":  "",
    "OSArchitecture":  "64bitovì",
    "OSLanguage":  1029,
    "OSProductSuite":  256,
    "OSType":  18,
    "OtherTypeDescription":  null,
    "PAEEnabled":  null,
    "PlusProductID":  null,
    "PlusVersionNumber":  null,
    "PortableOperatingSystem":  false,
    "Primary":  true,
    "ProductType":  1,
    "RegisteredUser":  "Neuromancer@outlook.cz",
    "SerialNumber":  "00330-80000-00000-AA186",
    "ServicePackMajorVersion":  0,
    "ServicePackMinorVersion":  0,
    "SizeStoredInPagingFiles":  6029312,
    "Status":  "OK",
    "SuiteMask":  272,
    "SystemDevice":  "\\Device\\HarddiskVolume2",
    "SystemDirectory":  "C:\\WINDOWS\\system32",
    "SystemDrive":  "C:",
    "TotalSwapSpaceSize":  null,
    "TotalVirtualMemorySize":  14375244,
    "TotalVisibleMemorySize":  8345932,
    "Version":  "10.0.19042",
    "WindowsDirectory":  "C:\\WINDOWS"
}
